asit/__init__.py
asit/asit.py
asit/test.py
asit-0.5.dist-info/DESCRIPTION.rst
asit-0.5.dist-info/METADATA
asit-0.5.dist-info/RECORD
asit-0.5.dist-info/WHEEL
asit-0.5.dist-info/metadata.json
asit-0.5.dist-info/top_level.txt
