Metadata-Version: 2.0
Name: asit
Version: 0.5
Summary: Advanced System Information Toolbox Python Library
Home-page: https://github.com/aligholamee/asit
Author: Ali Gholami
Author-email: aligholami7596@gmail.com
License: MIT
Keywords: SYSTEM INFO CPU MEMORY OS PYTHON
Platform: any
Requires-Python: >3.5
Requires-Dist: codecov
